fastgenomics/FASTGenomicsPlatformUpdater.py
fastgenomics/__init__.py
fastgenomics/fg.py
fastgenomics-3.4.0.dist-info/WHEEL
fastgenomics-3.4.0.dist-info/METADATA
fastgenomics-3.4.0.dist-info/RECORD
