Metadata-Version: 2.1
Name: fastgenomics
Version: 3.4.0
Summary: FASTGenomics base library
Home-page: https://beta.fastgenomics.org
Author: FASTGenomics
Author-email: team@fastgenomics.org
Requires-Dist: requests >=2
Requires-Dist: tqdm >=4
